server/__init__.py
server/server.py
server/common/__init__.py
server/common/descripts.py
server/common/handler.py
server/common/metaclasses.py
server/common/parser.py
server/server/__init__.py
server/server/config_window.py
server/server/core.py
server/server/database.py
server/server/login_required.py
server/server/server_gui.py
server/server/statistic.py
server/unit_tests/__init__.py
fine_messanger_server-0.0.1.dist-info/METADATA
fine_messanger_server-0.0.1.dist-info/WHEEL
fine_messanger_server-0.0.1.dist-info/top_level.txt
fine_messanger_server-0.0.1.dist-info/RECORD
